modelq_analytics/__init__.py
modelq_analytics/api/__init__.py
modelq_analytics/api/analytics.py
modelq_analytics-0.1.3.dist-info/METADATA
modelq_analytics-0.1.3.dist-info/WHEEL
modelq_analytics-0.1.3.dist-info/RECORD
