Metadata-Version: 2.3
Name: modelq-analytics
Version: 0.1.3
Summary: Analytics dashboard for modelq.
Author: Tanmay patil
Author-email: tanmaypatil3151@gmail.com
Requires-Python: >=3.10,<4.0
Classifier: Programming Language :: Python :: 3
Classifier: Programming Language :: Python :: 3.10
Classifier: Programming Language :: Python :: 3.11
Classifier: Programming Language :: Python :: 3.12
Classifier: Programming Language :: Python :: 3.13
Requires-Dist: modelq (>=0.1.14,<0.2.0)
Requires-Dist: uvicorn[standard] (>=0.27.1,<0.28.0)
